dynatrace_extension_models/__init__.py
dynatrace_extension_models/pydantic_interop.py
dt_extensions_models-0.2.0.dist-info/LICENSE
dt_extensions_models-0.2.0.dist-info/METADATA
dt_extensions_models-0.2.0.dist-info/WHEEL
dt_extensions_models-0.2.0.dist-info/RECORD
